pyorthogonalrouting/Common.py
pyorthogonalrouting/Configuration.py
pyorthogonalrouting/ConnectorPoint.py
pyorthogonalrouting/Functions.py
pyorthogonalrouting/Grid.py
pyorthogonalrouting/LeftTopRightBottom.py
pyorthogonalrouting/Line.py
pyorthogonalrouting/OrthogonalConnector.py
pyorthogonalrouting/OrthogonalConnectorByProduct.py
pyorthogonalrouting/OrthogonalConnectorOptions.py
pyorthogonalrouting/Point.py
pyorthogonalrouting/PointGraph.py
pyorthogonalrouting/PointNode.py
pyorthogonalrouting/Rect.py
pyorthogonalrouting/Rectangle.py
pyorthogonalrouting/Size.py
pyorthogonalrouting/__init__.py
pyorthogonalrouting/_version.py
pyorthogonalrouting/py.typed
pyorthogonalrouting/enumerations/BendDirection.py
pyorthogonalrouting/enumerations/Direction.py
pyorthogonalrouting/enumerations/Side.py
pyorthogonalrouting/enumerations/__init__.py
pyorthogonalrouting/enumerations/py.typed
pyorthogonalrouting-2.0.0.dist-info/licenses/LICENSE
pyorthogonalrouting-2.0.0.dist-info/METADATA
pyorthogonalrouting-2.0.0.dist-info/WHEEL
pyorthogonalrouting-2.0.0.dist-info/top_level.txt
pyorthogonalrouting-2.0.0.dist-info/RECORD
