Metadata-Version: 2.4
Name: pyorthogonalrouting
Version: 2.0.0
Summary: Yet another orthogonal router
Author-email: "Humberto A. Sanchez II" <Humbert.A.Sanchez.II@gmail.com>
Maintainer-email: "Humberto A. Sanchez II" <Humbert.A.Sanchez.II@gmail.com>
License-Expression: AGPL-1.0-or-later
Project-URL: Repository, https://github.com/hasii2011/py-orthogonal-routing
Keywords: orthogonal,routing,python,pyut
Classifier: Programming Language :: Python
Classifier: Intended Audience :: Developers
Classifier: Operating System :: MacOS :: MacOS X
Classifier: Topic :: Software Development :: Libraries :: Python Modules
License-File: LICENSE
Requires-Dist: codeallybasic>=1.30.0
Requires-Dist: Pypubsub==4.0.3
Provides-Extra: test
Requires-Dist: mypy==1.19.0; extra == "test"
Requires-Dist: html-testRunner~=1.2.1; extra == "test"
Provides-Extra: deploy
Requires-Dist: wheel==0.45.1; extra == "deploy"
Requires-Dist: setuptools==80.9.0; extra == "deploy"
Requires-Dist: twine==6.2.0; extra == "deploy"
Requires-Dist: build==1.3.0; extra == "deploy"
Provides-Extra: demo
Requires-Dist: wxPython==4.2.4; extra == "demo"
Dynamic: license-file
